cache/cache.v
module cache_controller (
    clk,
    rst_n,
    // CPU Interface
    cpu_req_addr,
    cpu_req_datain,
    cpu_req_dataout,
    cpu_req_rw,
    cpu_req_valid,
    cache_ready,
    // Main Memory Interface
    mem_req_addr,
    mem_req_datain,
    mem_req_dataout,
    mem_req_rw,
    mem_req_valid,
    mem_req_ready
);

parameter IDLE        = 2'b00;
parameter COMPARE_TAG = 2'b01;
parameter ALLOCATE    = 2'b10;
parameter WRITE_BACK  = 2'b11;

input clk;
input rst_n;

// CPU request to cache controller
input [31:0] cpu_req_addr;
input [127:0] cpu_req_datain;
output [31:0] cpu_req_dataout;
input cpu_req_rw; // 1=write, 0=read
input cpu_req_valid;

// Main memory request from cache controller
output [31:0] mem_req_addr;
input [127:0] mem_req_datain;
output [127:0] mem_req_dataout;
output mem_req_rw;
output mem_req_valid;
input mem_req_ready;

// Cache ready
output cache_ready;

// Cache consists of tag memory and data memory
reg [19:0] tag_mem [0:1023];
reg [127:0] data_mem [0:1023];

reg [1:0] present_state, next_state;
reg [31:0] cpu_req_dataout, next_cpu_req_dataout;
reg [31:0] cache_read_data;
reg cache_ready, next_cache_ready;
reg [31:0] mem_req_addr, next_mem_req_addr;
reg mem_req_rw, next_mem_req_rw;
reg mem_req_valid, next_mem_req_valid;
reg [127:0] mem_req_dataout, next_mem_req_dataout;
reg write_datamem_mem;
reg write_datamem_cpu;
reg tagmem_enable;
reg valid_bit, dirty_bit;

reg [31:0] cpu_req_addr_reg, next_cpu_req_addr_reg;
reg [127:0] cpu_req_datain_reg, next_cpu_req_datain_reg;
reg cpu_req_rw_reg, next_cpu_req_rw_reg;

wire [17:0] cpu_addr_tag;
wire [9:0] cpu_addr_index;
wire [1:0] cpu_addr_blk_offset;
wire hit;

// CPU Address breakdown
assign cpu_addr_tag         = cpu_req_addr_reg[31:14];
assign cpu_addr_index       = cpu_req_addr_reg[13:4];
assign cpu_addr_blk_offset  = cpu_req_addr_reg[3:2];

// Cache lookup
wire [19:0] tag_mem_entry  = tag_mem[cpu_addr_index];
wire [127:0] data_mem_entry = data_mem[cpu_addr_index];
assign hit = tag_mem_entry[19] && (cpu_addr_tag == tag_mem_entry[17:0]);

// Initialize memories to zero
integer init_i;
initial begin
    for (init_i = 0; init_i < 1024; init_i = init_i + 1) begin
        tag_mem[init_i] = 20'b0;
        data_mem[init_i] = 128'b0;
    end
    
    // VCD dumping for GTKwave
    `ifdef COCOTB_SIM
    $dumpfile("waveforms.vcd");
    $dumpvars(0, cache_controller);
    $display("VCD dumping enabled for GTKwave");
    `endif
end

// Sequential logic
always @(posedge clk or negedge rst_n) begin
    if (!rst_n) begin
        present_state    <= IDLE;
        cpu_req_dataout  <= 32'd0;
        cache_ready      <= 1'b0;
        mem_req_addr     <= 32'd0;
        mem_req_rw       <= 1'b0;
        mem_req_valid    <= 1'b0;
        mem_req_dataout  <= 128'd0;
        cpu_req_addr_reg <= 32'd0;
        cpu_req_datain_reg <= 128'd0;
        cpu_req_rw_reg   <= 1'b0;
    end else begin
        // Update memories
        if (tagmem_enable) begin
            tag_mem[cpu_addr_index] <= {4'b0, valid_bit, dirty_bit, cpu_addr_tag};
        end
        
        if (write_datamem_mem) begin
            data_mem[cpu_addr_index] <= mem_req_datain;
        end else if (write_datamem_cpu) begin
            data_mem[cpu_addr_index] <= cpu_req_datain_reg;
        end
        
        // Update registers
        present_state    <= next_state;
        cpu_req_dataout  <= next_cpu_req_dataout;
        cache_ready      <= next_cache_ready;
        mem_req_addr     <= next_mem_req_addr;
        mem_req_rw       <= next_mem_req_rw;
        mem_req_valid    <= next_mem_req_valid;
        mem_req_dataout  <= next_mem_req_dataout;
        cpu_req_addr_reg <= next_cpu_req_addr_reg;
        cpu_req_datain_reg <= next_cpu_req_datain_reg;
        cpu_req_rw_reg   <= next_cpu_req_rw_reg;
    end
end

// Combinational logic
always @(*) begin
    // Default values
    write_datamem_mem    = 1'b0;
    write_datamem_cpu    = 1'b0;
    valid_bit            = 1'b0;
    dirty_bit            = 1'b0;
    tagmem_enable        = 1'b0;
    next_state           = present_state;
    next_cpu_req_dataout = cpu_req_dataout;
    next_cache_ready     = 1'b1;
    next_mem_req_addr    = mem_req_addr;
    next_mem_req_rw      = mem_req_rw;
    next_mem_req_valid   = mem_req_valid;
    next_mem_req_dataout = mem_req_dataout;
    next_cpu_req_addr_reg  = cpu_req_addr_reg;
    next_cpu_req_datain_reg  = cpu_req_datain_reg;
    next_cpu_req_rw_reg  = cpu_req_rw_reg;

    // Data selection mux
    case (cpu_addr_blk_offset)
        2'b00: cache_read_data = data_mem_entry[31:0];
        2'b01: cache_read_data = data_mem_entry[63:32];
        2'b10: cache_read_data = data_mem_entry[95:64];
        2'b11: cache_read_data = data_mem_entry[127:96];
        default: cache_read_data = 32'd0;
    endcase

    // State machine
    case (present_state)
        IDLE: begin
            if (cpu_req_valid) begin
                next_cpu_req_addr_reg = cpu_req_addr;
                next_cpu_req_datain_reg = cpu_req_datain;
                next_cpu_req_rw_reg = cpu_req_rw;
                next_cache_ready = 1'b0;
                next_state = COMPARE_TAG;
            end
        end

        COMPARE_TAG: begin
            if (hit) begin
                if (!cpu_req_rw_reg) begin // Read hit
                    next_cpu_req_dataout = cache_read_data;
                    next_state = IDLE;
                end else begin // Write hit
                    write_datamem_cpu = 1'b1;
                    valid_bit = 1'b1;
                    dirty_bit = 1'b1;
                    tagmem_enable = 1'b1;
                    next_state = IDLE;
                end
            end else begin // Miss
                next_cache_ready = 1'b0;
                if (tag_mem_entry[18]) begin // Dirty
                    next_mem_req_addr = {tag_mem_entry[17:0], cpu_addr_index, 4'b0000};
                    next_mem_req_dataout = data_mem_entry;
                    next_mem_req_rw = 1'b1;
                    next_mem_req_valid = 1'b1;
                    next_state = WRITE_BACK;
                end else begin // Clean
                    if (!cpu_req_rw_reg) begin // Read
                        next_mem_req_addr = {cpu_req_addr_reg[31:4], 4'b0000};
                        next_mem_req_rw = 1'b0;
                        next_mem_req_valid = 1'b1;
                        next_state = ALLOCATE;
                    end else begin // Write
                        write_datamem_cpu = 1'b1;
                        valid_bit = 1'b1;
                        dirty_bit = 1'b1;
                        tagmem_enable = 1'b1;
                        next_state = IDLE;
                    end
                end
            end
        end

        ALLOCATE: begin
            next_mem_req_valid = 1'b0;
            next_cache_ready = 1'b0;
            if (mem_req_ready) begin
                write_datamem_mem = 1'b1;
                valid_bit = 1'b1;
                dirty_bit = 1'b0;
                tagmem_enable = 1'b1;
                next_state = COMPARE_TAG;
            end
        end

        WRITE_BACK: begin
            next_cache_ready = 1'b0;
            next_mem_req_valid = 1'b0;
            if (mem_req_ready) begin
                if (!cpu_req_rw_reg) begin
                    next_mem_req_addr = {cpu_req_addr_reg[31:4], 4'b0000};
                    next_mem_req_rw = 1'b0;
                    next_mem_req_valid = 1'b1;
                    next_state = ALLOCATE;
                end else begin
                    write_datamem_cpu = 1'b1;
                    valid_bit = 1'b1;
                    dirty_bit = 1'b1;
                    tagmem_enable = 1'b1;
                    next_state = IDLE;
                end
            end
        end

        default: next_state = IDLE;
    endcase
end

endmodule

cache/waveforms.vcd
$date
	Sat Aug 23 04:51:38 2025
$end
$version
	Icarus Verilog
$end
$timescale
	1ps
$end
$scope module cache_controller $end
$var wire 1 ! clk $end
$var wire 32 " cpu_req_addr [31:0] $end
$var wire 128 # cpu_req_datain [127:0] $end
$var wire 1 $ cpu_req_rw $end
$var wire 1 % cpu_req_valid $end
$var wire 128 & data_mem_entry [127:0] $end
$var wire 1 ' hit $end
$var wire 128 ( mem_req_datain [127:0] $end
$var wire 1 ) mem_req_ready $end
$var wire 1 * rst_n $end
$var wire 20 + tag_mem_entry [19:0] $end
$var wire 18 , cpu_addr_tag [17:0] $end
$var wire 10 - cpu_addr_index [9:0] $end
$var wire 2 . cpu_addr_blk_offset [1:0] $end
$var parameter 2 / ALLOCATE $end
$var parameter 2 0 COMPARE_TAG $end
$var parameter 2 1 IDLE $end
$var parameter 2 2 WRITE_BACK $end
$var reg 32 3 cache_read_data [31:0] $end
$var reg 1 4 cache_ready $end
$var reg 32 5 cpu_req_addr_reg [31:0] $end
$var reg 128 6 cpu_req_datain_reg [127:0] $end
$var reg 32 7 cpu_req_dataout [31:0] $end
$var reg 1 8 cpu_req_rw_reg $end
$var reg 1 9 dirty_bit $end
$var reg 32 : mem_req_addr [31:0] $end
$var reg 128 ; mem_req_dataout [127:0] $end
$var reg 1 < mem_req_rw $end
$var reg 1 = mem_req_valid $end
$var reg 1 > next_cache_ready $end
$var reg 32 ? next_cpu_req_addr_reg [31:0] $end
$var reg 128 @ next_cpu_req_datain_reg [127:0] $end
$var reg 32 A next_cpu_req_dataout [31:0] $end
$var reg 1 B next_cpu_req_rw_reg $end
$var reg 32 C next_mem_req_addr [31:0] $end
$var reg 128 D next_mem_req_dataout [127:0] $end
$var reg 1 E next_mem_req_rw $end
$var reg 1 F next_mem_req_valid $end
$var reg 2 G next_state [1:0] $end
$var reg 2 H present_state [1:0] $end
$var reg 1 I tagmem_enable $end
$var reg 1 J valid_bit $end
$var reg 1 K write_datamem_cpu $end
$var reg 1 L write_datamem_mem $end
$var integer 32 M init_i [31:0] $end
$upscope $end
$enddefinitions $end
$comment Show the parameter values. $end
$dumpall
b11 2
b0 1
b1 0
b10 /
$end
#0
$dumpvars
b10000000000 M
0L
0K
0J
0I
b0 H
b0 G
0F
0E
b0 D
b0 C
0B
b0 A
b0 @
b0 ?
1>
0=
0<
b0 ;
b0 :
09
08
b0 7
b0 6
b0 5
04
b0 3
b0 .
b0 -
b0 ,
b0 +
0*
z)
bz (
0'
b0 &
0%
0$
b0 #
b0 "
1!
$end
#5000
0!
#10000
1!
#15000
0!
#20000
1!
#25000
0!
#30000
1!
#35000
0!
#40000
1!
#45000
0!
#50000
1!
#55000
0!
#60000
1!
#65000
0!
#70000
1!
#75000
0!
#80000
1!
#85000
0!
#90000
1!
#95000
0!
#100000
1*
1!
#105000
0!
#110000
14
1!
#115000
0!
#120000
1!
#125000
0!
#130000
1!
#135000
0!
#140000
1!
#145000
0!
#150000
1!
#155000
0!
#160000
1!
#165000
0!
#170000
1!
#175000
0!
#180000
1!
#185000
0!
#190000
1!
#195000
0!
#200000
1!
#205000
0!
#210000
1!
#215000
0!
#220000
1!
#225000
0!
#230000
1!
#235000
0!
#240000
1!
#245000
0!
#250000
1!
#255000
0!
#260000
1!
#265000
0!
#270000
1!
#275000
0!
#280000
1!
#285000
0!
#290000
1!
#295000
0!
#300000
1!
#305000
0!
#310000
1!
#315000
0!
#320000
1!
#325000
0!
#330000
1!
#335000
0!
#340000
1!
#345000
0!
#350000
1!
#355000
0!
#360000
1!
#365000
0!
#370000
1!
#375000
0!
#380000
1!
#385000
0!
#390000
1!
#395000
0!
#400000
1!
#405000
0!
#410000
1!
#415000
0!
#420000
1!
#425000
0!
#430000
1!
#435000
0!
#440000
1!
#445000
0!
#450000
1!
#455000
0!
#460000
1!
#465000
0!
#470000
1!
#475000
0!
#480000
1!
#485000
0!
#490000
1!
#495000
0!
#500000
1!
#505000
0!
#510000
1!
#515000
0!
#520000
1!
#525000
0!
#530000
1!
#535000
0!
#540000
1!
#545000
0!
#550000
1!
#555000
0!
#560000
1!
#565000
0!
#570000
1!
#575000
0!
#580000
1!
#585000
0!
#590000
1!
#595000
0!
#600000
1!
#605000
0!
#610000
b1 G
0>
b1000000000000 ?
b1000000000000 "
1%
1!
#615000
0!
#620000
b100000000 -
b10 G
1F
b1000000000000 C
0>
b1000000000000 5
04
b1 H
1!
#625000
0!
#630000
0F
0>
1=
b1000000000000 :
b10 H
1!
#635000
0!
#640000
0>
0=
1!
#645000
0!
#650000
1!
#655000
0!
#660000
1!
#665000
0!
#670000
1!
#675000
0!
#680000
1!
#685000
0!
#690000
1!
#695000
0!
#700000
1!
#705000
0!
#710000
1!
#715000
0!
#720000
1!
#725000
0!
#730000
1!
#735000
0!
#740000
1!
#745000
0!
#750000
1!
#755000
0!
#760000
1!
#765000
0!
#770000
1!
#775000
0!
#780000
1!
#785000
0!
#790000
1!
#795000
0!
#800000
1!
#805000
0!
#810000
0>
0%
1!
#815000
0!
#820000
1!
#825000
0!
#830000
1!
#835000
0!
#840000
1!
#845000
0!
#850000
1!
#855000
0!
#860000
1!
#865000
0!
#870000
1!
#875000
0!
#880000
1!
#885000
0!
#890000
1!
#895000
0!
#900000
1!
#905000
0!
#910000
1!
#915000
0!
#920000
1!
#925000
0!
#930000
1!
#935000
0!
#940000
1!
#945000
0!
#950000
1!
#955000
0!
#960000
1!
#965000
0!
#970000
1!
#975000
0!
#980000
1!
#985000
0!
#990000
1!
#995000
0!
#1000000
1!
#1005000
0!
#1010000
1!
#1010001
b0 -
b0 ?
b0 C
b0 G
b0 5
b0 :
b0 H
1>
b0 "
0*
#1015001
0!
#1020001
1!
#1025001
0!
#1030001
1!
#1035001
0!
#1040001
1!
#1045001
0!
#1050001
1!
#1055001
0!
#1060001
1!
#1065001
0!
#1070001
1!
#1075001
0!
#1080001
1!
#1085001
0!
#1090001
1!
#1095001
0!
#1100001
1!
#1105001
0!
#1110001
1*
1!
#1115001
0!
#1120001
14
1!
